riptide_mission_control/__init__.py
riptide_mission_control/main.py
riptide_mission_control-0.3.0.dist-info/LICENSE
riptide_mission_control-0.3.0.dist-info/METADATA
riptide_mission_control-0.3.0.dist-info/WHEEL
riptide_mission_control-0.3.0.dist-info/entry_points.txt
riptide_mission_control-0.3.0.dist-info/top_level.txt
riptide_mission_control-0.3.0.dist-info/RECORD
